{
  "lessonId": "10-5",
  "title": "Surface Area of Pyramids",
  "standard": "6.G.4",
  "emoji": "🔺",
  "unitName": "Unit 10 · Lesson 5",
  "why": "A pyramid's surface is one <strong>base</strong> plus several <strong>triangle faces</strong>. So you need the <strong>area of a rectangle/square</strong> for the base, the <strong>area of a triangle</strong> (½ × base × height) for each side, and the skill to <strong>add several areas</strong>. Warm those up first.",
  "skills": [
    "Area of a square/rectangle",
    "Area of a triangle (½ × b × h)",
    "Adding several areas",
    "Identifying faces of a pyramid"
  ],
  "diagnostic": [
    {
      "q": "Area of a square that is <strong>4 on each side</strong>?",
      "ans": "b",
      "opts": [
        { "v": "a", "t": "8" },
        { "v": "b", "t": "16" },
        { "v": "c", "t": "12" },
        { "v": "d", "t": "4" }
      ]
    },
    {
      "q": "Area of a triangle with base 6 and height 4: <strong>½ × 6 × 4</strong>?",
      "ans": "c",
      "opts": [
        { "v": "a", "t": "24" },
        { "v": "b", "t": "10" },
        { "v": "c", "t": "12" },
        { "v": "d", "t": "5" }
      ]
    },
    {
      "q": "A square pyramid has 1 square base and how many triangle faces?",
      "ans": "a",
      "opts": [
        { "v": "a", "t": "4" },
        { "v": "b", "t": "3" },
        { "v": "c", "t": "6" }
      ]
    }
  ],
  "learn": {
    "heading": "Base area + triangle faces",
    "intro": "<p>A square pyramid has <strong>1 square base</strong> and <strong>4 triangle faces</strong>. Find the base area (side × side), find each triangle's area (<strong>½ × base × height</strong>), then <strong>add</strong> the base and all the triangles. Answer is in <strong>square units</strong>.</p>",
    "examples": [
      "<strong>Triangle area:</strong> ½ × 6 × 4 → first 6 × 4 = 24, then half of 24 = <strong>12</strong>.",
      "<strong>Add it up:</strong> base 16 plus four triangles of 12 each = 16 + 12 + 12 + 12 + 12 = <strong>64</strong> square units."
    ]
  },
  "tiers": [
    {
      "level": 0,
      "intro": "Find a triangle's area one step at a time.",
      "items": [
        {
          "type": "num",
          "q": "A. First: base × height = 4 × 6 = ___",
          "ans": 24,
          "hint": "4 × 6 = 24."
        },
        {
          "type": "num",
          "q": "B. Now take half: half of 24 = ___",
          "ans": 12,
          "hint": "24 ÷ 2 = 12."
        },
        {
          "type": "num",
          "q": "C. So the triangle area ½ × 4 × 6 = ___",
          "ans": 12,
          "hint": "4 × 6 = 24, then half is 12."
        }
      ]
    },
    {
      "level": 1,
      "intro": "Base plus triangles.",
      "items": [
        {
          "type": "num",
          "q": "A. Area of a square base, side 5 (5 × 5) = ___",
          "ans": 25,
          "hint": "5 × 5 = 25."
        },
        {
          "type": "num",
          "q": "B. Triangle area: ½ × 8 × 3 = ___",
          "ans": 12,
          "hint": "8 × 3 = 24, then half is 12."
        },
        {
          "type": "num",
          "q": "C. Add the base and 4 triangles: 16 + 10 + 10 + 10 + 10 = ___",
          "ans": 56,
          "hint": "Four 10s = 40, then 40 + 16 = 56."
        }
      ]
    },
    {
      "level": 2,
      "intro": "Stretch: full pyramid surface area.",
      "items": [
        {
          "type": "num",
          "q": "A. A square pyramid: base 6 × 6, four triangles each ½ × 6 × 5. What is the total surface area?",
          "ans": 96,
          "hint": "Base = 36. Each triangle = ½ × 6 × 5 = 15, four of them = 60. Total 36 + 60 = 96."
        },
        {
          "type": "num",
          "q": "B. Four triangle faces each have area 9. What is their combined area? (square units)",
          "ans": 36,
          "hint": "4 × 9 = 36."
        }
      ]
    }
  ],
  "exit": [
    {
      "type": "num",
      "q": "1. Area of a triangle: <strong>½ × 10 × 4</strong> = ___",
      "ans": 20,
      "hint": "10 × 4 = 40, then half is 20."
    },
    {
      "type": "mc",
      "q": "2. A square pyramid is made of which faces?",
      "ans": "b",
      "opts": [
        { "v": "a", "t": "6 squares" },
        { "v": "b", "t": "1 square base + 4 triangles" },
        { "v": "c", "t": "2 squares + 4 rectangles" },
        { "v": "d", "t": "4 triangles only" }
      ],
      "hint": "A square pyramid has 1 square base and 4 triangular sides."
    }
  ]
}
