{
  "lessonId": "2-1",
  "title": "Interpret Division of Fractions",
  "standard": "6.NS.1",
  "emoji": "🍕",
  "unitName": "Unit 2 · Lesson 1",
  "why": "Before you can <em>interpret</em> what fraction division means, you need to picture <strong>equal groups</strong> and <strong>equal sharing</strong> — the same ideas behind whole-number division. Get those warm and \"how many halves fit in 3?\" makes sense.",
  "skills": [
    "Meaning of a fraction",
    "Equal groups / equal sharing",
    "Multiplication & division facts",
    "How many of this fit in that"
  ],
  "diagnostic": [
    {
      "q": "In the fraction <strong>3/4</strong>, which number is the <strong>denominator</strong> (total equal parts)?",
      "ans": "b",
      "opts": [
        { "v": "a", "t": "3" },
        { "v": "b", "t": "4" },
        { "v": "c", "t": "7" },
        { "v": "d", "t": "1" }
      ]
    },
    {
      "q": "<strong>12 ÷ 3</strong> means: how many groups of 3 are in 12. What is it?",
      "ans": "c",
      "opts": [
        { "v": "a", "t": "9" },
        { "v": "b", "t": "15" },
        { "v": "c", "t": "4" },
        { "v": "d", "t": "36" }
      ]
    },
    {
      "q": "How many <strong>halves</strong> make <strong>1 whole</strong>?",
      "ans": "a",
      "opts": [
        { "v": "a", "t": "2" },
        { "v": "b", "t": "3" },
        { "v": "c", "t": "1" },
        { "v": "d", "t": "4" }
      ]
    }
  ],
  "learn": {
    "heading": "What does division mean?",
    "intro": "<p><strong>Division</strong> can ask two things: <em>how many equal groups</em> (12 ÷ 3 = how many 3s in 12) or <em>how big is each share</em> (12 ÷ 3 = share 12 into 3 equal piles). Both ideas carry straight into fractions.</p>",
    "examples": [
      "<strong>How many fit:</strong> 6 ÷ 2 asks \"how many 2s are in 6?\" → 3.",
      "<strong>Fraction version:</strong> \"How many halves are in 1 whole?\" → 2, because two 1/2 pieces make a whole."
    ]
  },
  "tiers": [
    {
      "level": 0,
      "intro": "Let's count equal groups one step at a time.",
      "items": [
        {
          "type": "num",
          "q": "A. How many equal groups of 2 are in 6? Fill in: 2 × ___ = 6",
          "ans": 3,
          "hint": "2 × 3 = 6, so there are 3 groups of 2."
        },
        {
          "type": "num",
          "q": "B. How many halves make 1 whole pizza?",
          "ans": 2,
          "hint": "Two 1/2 pieces snap together to make 1 whole."
        },
        {
          "type": "num",
          "q": "C. <strong>10 ÷ 5</strong> = ?",
          "ans": 2,
          "hint": "How many 5s are in 10? 5 × 2 = 10."
        }
      ]
    },
    {
      "level": 1,
      "intro": "Read what the division is asking, then answer.",
      "items": [
        {
          "type": "num",
          "q": "A. How many fourths (1/4) make 1 whole?",
          "ans": 4,
          "hint": "Four 1/4 pieces make a whole: 1/4 + 1/4 + 1/4 + 1/4 = 1."
        },
        {
          "type": "mc",
          "q": "B. <strong>15 ÷ 3</strong> means \"how many 3s are in 15?\" What is it?",
          "ans": "c",
          "opts": [
            { "v": "a", "t": "12" },
            { "v": "b", "t": "18" },
            { "v": "c", "t": "5" },
            { "v": "d", "t": "45" }
          ],
          "hint": "3 × 5 = 15, so five 3s fit in 15."
        }
      ]
    },
    {
      "level": 2,
      "intro": "Stretch right up to fraction division.",
      "items": [
        {
          "type": "num",
          "q": "A. How many halves (1/2) are in <strong>2 whole</strong> pizzas?",
          "ans": 4,
          "hint": "Each whole holds 2 halves, and 2 wholes → 2 × 2 = 4 halves."
        },
        {
          "type": "num",
          "q": "B. How many thirds (1/3) are in <strong>1 whole</strong>?",
          "ans": 3,
          "hint": "Three 1/3 pieces make a whole."
        }
      ]
    }
  ],
  "exit": [
    {
      "type": "mc",
      "q": "1. What does <strong>8 ÷ 4</strong> ask?",
      "ans": "a",
      "opts": [
        { "v": "a", "t": "How many groups of 4 are in 8?" },
        { "v": "b", "t": "What is 8 + 4?" },
        { "v": "c", "t": "What is 8 × 4?" }
      ],
      "hint": "Division asks how many equal groups fit — and the answer is 2."
    },
    {
      "type": "num",
      "q": "2. How many halves (1/2) are in <strong>1 whole</strong>?",
      "ans": 2,
      "hint": "Two 1/2 pieces make a whole."
    }
  ]
}
