{
  "summary": {
    "scannedHtml": 1077,
    "lessons": 75,
    "errors": 19,
    "warnings": 10,
    "info": 1
  },
  "findings": [
    {
      "severity": "error",
      "category": "link",
      "message": "broken link → ../../_art/lessons/u1-l5l6/cover.png",
      "where": "graphic-novels/lessons/u1-l5l6/graphic-novel-1.html"
    },
    {
      "severity": "error",
      "category": "link",
      "message": "broken link → ../../_art/lessons/u1-l5l6/act1.png",
      "where": "graphic-novels/lessons/u1-l5l6/graphic-novel-1.html"
    },
    {
      "severity": "error",
      "category": "link",
      "message": "broken link → ../../_art/lessons/u1-l5l6/act2.png",
      "where": "graphic-novels/lessons/u1-l5l6/graphic-novel-1.html"
    },
    {
      "severity": "error",
      "category": "link",
      "message": "broken link → ../../_art/lessons/u1-l5l6/final.png",
      "where": "graphic-novels/lessons/u1-l5l6/graphic-novel-1.html"
    },
    {
      "severity": "error",
      "category": "link",
      "message": "broken link → ../../_art/lessons/u1-l5l6/complete.png",
      "where": "graphic-novels/lessons/u1-l5l6/graphic-novel-1.html"
    },
    {
      "severity": "error",
      "category": "link",
      "message": "broken link → ../../_art/lessons/u1-l5l6/cover.png",
      "where": "graphic-novels/lessons/u1-l5l6/graphic-novel-2.html"
    },
    {
      "severity": "error",
      "category": "link",
      "message": "broken link → ../../_art/lessons/u1-l5l6/act1.png",
      "where": "graphic-novels/lessons/u1-l5l6/graphic-novel-2.html"
    },
    {
      "severity": "error",
      "category": "link",
      "message": "broken link → ../../_art/lessons/u1-l5l6/act2.png",
      "where": "graphic-novels/lessons/u1-l5l6/graphic-novel-2.html"
    },
    {
      "severity": "error",
      "category": "link",
      "message": "broken link → ../../_art/lessons/u1-l5l6/final.png",
      "where": "graphic-novels/lessons/u1-l5l6/graphic-novel-2.html"
    },
    {
      "severity": "error",
      "category": "link",
      "message": "broken link → ../../_art/lessons/u1-l5l6/complete.png",
      "where": "graphic-novels/lessons/u1-l5l6/graphic-novel-2.html"
    },
    {
      "severity": "error",
      "category": "link",
      "message": "broken link → ../../_art/lessons/u1-l7/cover.png",
      "where": "graphic-novels/lessons/u1-l7/graphic-novel-1.html"
    },
    {
      "severity": "error",
      "category": "link",
      "message": "broken link → ../../_art/lessons/u1-l7/act1.png",
      "where": "graphic-novels/lessons/u1-l7/graphic-novel-1.html"
    },
    {
      "severity": "error",
      "category": "link",
      "message": "broken link → ../../_art/lessons/u1-l7/final.png",
      "where": "graphic-novels/lessons/u1-l7/graphic-novel-1.html"
    },
    {
      "severity": "error",
      "category": "link",
      "message": "broken link → ../../_art/lessons/u1-l7/complete.png",
      "where": "graphic-novels/lessons/u1-l7/graphic-novel-1.html"
    },
    {
      "severity": "error",
      "category": "link",
      "message": "broken link → ../../_art/lessons/u1-l7/cover.png",
      "where": "graphic-novels/lessons/u1-l7/graphic-novel-2.html"
    },
    {
      "severity": "error",
      "category": "link",
      "message": "broken link → ../../_art/lessons/u1-l7/act1.png",
      "where": "graphic-novels/lessons/u1-l7/graphic-novel-2.html"
    },
    {
      "severity": "error",
      "category": "link",
      "message": "broken link → ../../_art/lessons/u1-l7/final.png",
      "where": "graphic-novels/lessons/u1-l7/graphic-novel-2.html"
    },
    {
      "severity": "error",
      "category": "link",
      "message": "broken link → ../../_art/lessons/u1-l7/complete.png",
      "where": "graphic-novels/lessons/u1-l7/graphic-novel-2.html"
    },
    {
      "severity": "error",
      "category": "link",
      "message": "broken link → ./statistics-data/histogramhero/",
      "where": "index.html"
    },
    {
      "severity": "warn",
      "category": "flagship",
      "message": "both /lessons/1-1/ and /lessons/1-1-flagship/ are surfaced — possible duplicate flagship route",
      "where": "data/*.json"
    },
    {
      "severity": "warn",
      "category": "flagship",
      "message": "both /lessons/10-1/ and /lessons/10-1-flagship/ are surfaced — possible duplicate flagship route",
      "where": "data/*.json"
    },
    {
      "severity": "warn",
      "category": "flagship",
      "message": "both /lessons/2-1/ and /lessons/2-1-flagship/ are surfaced — possible duplicate flagship route",
      "where": "data/*.json"
    },
    {
      "severity": "warn",
      "category": "flagship",
      "message": "both /lessons/3-1/ and /lessons/3-1-flagship/ are surfaced — possible duplicate flagship route",
      "where": "data/*.json"
    },
    {
      "severity": "warn",
      "category": "flagship",
      "message": "both /lessons/4-1/ and /lessons/4-1-flagship/ are surfaced — possible duplicate flagship route",
      "where": "data/*.json"
    },
    {
      "severity": "warn",
      "category": "flagship",
      "message": "both /lessons/5-3/ and /lessons/5-3-flagship/ are surfaced — possible duplicate flagship route",
      "where": "data/*.json"
    },
    {
      "severity": "warn",
      "category": "flagship",
      "message": "both /lessons/6-1/ and /lessons/6-1-flagship/ are surfaced — possible duplicate flagship route",
      "where": "data/*.json"
    },
    {
      "severity": "warn",
      "category": "flagship",
      "message": "both /lessons/7-1/ and /lessons/7-1-flagship/ are surfaced — possible duplicate flagship route",
      "where": "data/*.json"
    },
    {
      "severity": "warn",
      "category": "flagship",
      "message": "both /lessons/8-1/ and /lessons/8-1-flagship/ are surfaced — possible duplicate flagship route",
      "where": "data/*.json"
    },
    {
      "severity": "warn",
      "category": "flagship",
      "message": "both /lessons/9-1/ and /lessons/9-1-flagship/ are surfaced — possible duplicate flagship route",
      "where": "data/*.json"
    },
    {
      "severity": "info",
      "category": "orphan",
      "message": "_template: lesson not referenced by routes/catalog/registry",
      "where": "/lessons/_template/"
    }
  ]
}