{
  "scenario_extract": {
    "session1": {
      "lesson_type": "geometry",
      "bonus_slides": [
        "area_model_diagram",
        "frayer_model",
        "real_world_transfer"
      ],
      "content_fingerprint": {
        "math_actions": ["identify", "calculate", "apply", "justify"],
        "representation_types": ["diagram", "equation"],
        "reasoning_demand": "explain",
        "vocabulary_load": "high"
      },
      "context": "James is putting a special restorative stain on the entire surface of the wooden chest. One can of stain covers about 35 square feet.",
      "iv_name": "face dimensions",
      "dv_name": "surface area",
      "iv_symbol": "",
      "dv_symbol": "SA",
      "rate": "",
      "equation": "",
      "formula": "SA = 2(lw) + 2(lh) + 2(wh)",
      "answer": 69,
      "answer_unit": "square feet",
      "all_numbers": [35, 5, 2, 3.5, 69, 2],
      "table_values": [],
      "graph_xmax": 10,
      "graph_ymax": 100,
      "graph_xlabel": "face dimensions",
      "graph_ylabel": "surface area",
      "image_slide": 4,
      "figure": {
        "type": "prism",
        "draw_params": {
          "b1": 5,
          "b2": null,
          "h": 3.5,
          "s1": 2,
          "s2": null,
          "s3": null,
          "unit": "ft",
          "decompose": true
        },
        "label_map": {
          "b1": "5 ft",
          "b2": null,
          "h": "3 1/2 ft"
        },
        "scale_hint": "small"
      },
      "problem_stems": {
        "guided": "James is putting a special restorative stain on the entire surface of the wooden chest. One can of stain covers about 35 square feet. How many cans of stain will James need?",
        "collaborative": "What is the area of each face?",
        "independent": ["", "", ""],
        "exit": ["", "", ""]
      },
      "vocabulary": [
        {
          "term": "surface area",
          "definition": "The surface area of a three-dimensional figure is the sum of the areas of the faces.",
          "visual_type": "shape"
        },
        {
          "term": "net",
          "definition": "A tool used to deconstruct a three-dimensional figure into its flat faces.",
          "visual_type": "diagram"
        },
        {
          "term": "rectangular prism",
          "definition": "A three-dimensional figure with 6 rectangular faces with 3 pairs of congruent faces.",
          "visual_type": "shape"
        },
        {
          "term": "face",
          "definition": "A flat surface of a three-dimensional figure.",
          "visual_type": "shape"
        },
        {
          "term": "congruent",
          "definition": "Having the same size and shape.",
          "visual_type": "diagram"
        }
      ],
      "misconceptions": [
        "Students may forget to include all 6 faces when calculating surface area.",
        "Students may confuse surface area with volume.",
        "Students may not recognize that opposite faces of a rectangular prism are congruent, leading to redundant calculations."
      ]
    },
    "session2": {
      "lesson_type": "geometry",
      "bonus_slides": [
        "area_model_diagram",
        "number_talk_frame",
        "frayer_model",
        "real_world_transfer"
      ],
      "content_fingerprint": {
        "math_actions": ["identify", "calculate", "apply", "transfer"],
        "representation_types": ["diagram", "equation"],
        "reasoning_demand": "transfer",
        "vocabulary_load": "high"
      },
      "context": "James is putting a special restorative stain on the entire surface of the wooden chest. One can of stain covers about 35 square feet.",
      "iv_name": "face dimensions",
      "dv_name": "surface area",
      "iv_symbol": "",
      "dv_symbol": "SA",
      "rate": "35 square feet per can",
      "equation": "",
      "formula": "SA = 2(lw) + 2(lh) + 2(wh)",
      "answer": 2,
      "answer_unit": "cans",
      "all_numbers": [35, 5, 2, 3.5, 69, 2],
      "table_values": [],
      "graph_xmax": 10,
      "graph_ymax": 100,
      "graph_xlabel": "face dimensions",
      "graph_ylabel": "surface area",
      "image_slide": 4,
      "figure": {
        "type": "prism",
        "draw_params": {
          "b1": 5,
          "b2": null,
          "h": 3.5,
          "s1": 2,
          "s2": null,
          "s3": null,
          "unit": "ft",
          "decompose": true
        },
        "label_map": {
          "b1": "5 ft",
          "b2": null,
          "h": "3 1/2 ft"
        },
        "scale_hint": "small"
      },
      "problem_stems": {
        "guided": "How many cans of stain will James need to cover the wooden chest with a surface area of 69 square feet if one can covers about 35 square feet?",
        "collaborative": "How can you find the surface area of the rectangular prism?",
        "independent": ["", "", ""],
        "exit": ["", "", ""]
      },
      "vocabulary": [
        {
          "term": "surface area",
          "definition": "The surface area of a three-dimensional figure is the sum of the areas of the faces.",
          "visual_type": "shape"
        },
        {
          "term": "net",
          "definition": "A tool used to deconstruct a three-dimensional figure into its flat faces.",
          "visual_type": "diagram"
        },
        {
          "term": "rectangular prism",
          "definition": "A three-dimensional figure with 6 rectangular faces with 3 pairs of congruent faces.",
          "visual_type": "shape"
        },
        {
          "term": "face",
          "definition": "A flat surface of a three-dimensional figure.",
          "visual_type": "shape"
        },
        {
          "term": "congruent",
          "definition": "Having the same size and shape.",
          "visual_type": "diagram"
        }
      ],
      "misconceptions": [
        "Students may round down the number of cans needed instead of rounding up, resulting in an insufficient quantity.",
        "Students may confuse surface area with volume when determining how much stain is needed.",
        "Students may incorrectly apply the division (69 ÷ 35) and not interpret the remainder correctly in context."
      ]
    }
  },
  "extracted_at": "2026-05-14T10:04:00.382739",
  "source": "/Users/joelneft/Documents/Projects/EduWonderLab/Lesson Plans/input/Editable Lesson Presentation_ Determine Surface Area of Prisms (1).pptx"
}
